{
    "keep": {
        "days": true,
        "amount": 1
    },
    "auditLog": "D:\\bdCalling\\Backend\\learnova-app-backend\\winston\\success\\.6ed9b4b711cb39ac1151a921263bf28ac2015b39-audit.json",
    "files": [
        {
            "date": 1739444784663,
            "name": "D:\\bdCalling\\Backend\\learnova-app-backend\\winston\\success\\13-02-2025-17-success.log",
            "hash": "5c9b9d819d17160907993543a5c748f5d878881fed6184a5e77cc951d3e1da23"
        },
        {
            "date": 1739453004665,
            "name": "D:\\bdCalling\\Backend\\learnova-app-backend\\winston\\success\\13-02-2025-19-success.log",
            "hash": "94dab81eb8d740fbfb892597b2f2a069a7271a833329b75a5b2a470b5bf014ec"
        }
    ],
    "hashType": "sha256"
}